pytemplate/__init__.py
pytemplate/main.py
templates/fastapi-template/cookiecutter.json
templates/fastapi-template/{{cookiecutter.project_name}}/Dockerfile
templates/fastapi-template/{{cookiecutter.project_name}}/Makefile
templates/fastapi-template/{{cookiecutter.project_name}}/README.md
templates/fastapi-template/{{cookiecutter.project_name}}/pyproject.toml
templates/fastapi-template/{{cookiecutter.project_name}}/{{cookiecutter.envfile}}
templates/fastapi-template/{{cookiecutter.project_name}}/tests/__init__.py
templates/fastapi-template/{{cookiecutter.project_name}}/tests/conftest.py
templates/fastapi-template/{{cookiecutter.project_name}}/tests/test_cli.py
templates/fastapi-template/{{cookiecutter.project_name}}/tests/test_example.py
templates/fastapi-template/{{cookiecutter.project_name}}/{{cookiecutter.package_name}}/__init__.py
templates/fastapi-template/{{cookiecutter.project_name}}/{{cookiecutter.package_name}}/cli.py
templates/fastapi-template/{{cookiecutter.project_name}}/{{cookiecutter.package_name}}/db.py
templates/fastapi-template/{{cookiecutter.project_name}}/{{cookiecutter.package_name}}/main.py
templates/fastapi-template/{{cookiecutter.project_name}}/{{cookiecutter.package_name}}/models.py
templates/fastapi-template/{{cookiecutter.project_name}}/{{cookiecutter.package_name}}/__pycache__/__init__.cpython-311.pyc
templates/fastapi-template/{{cookiecutter.project_name}}/{{cookiecutter.package_name}}/__pycache__/db.cpython-311.pyc
templates/fastapi-template/{{cookiecutter.project_name}}/{{cookiecutter.package_name}}/__pycache__/main.cpython-311.pyc
templates/fastapi-template/{{cookiecutter.project_name}}/{{cookiecutter.package_name}}/__pycache__/models.cpython-311.pyc
templates/fastapi-template/{{cookiecutter.project_name}}/{{cookiecutter.package_name}}/core/config.py
templates/fastapi-template/{{cookiecutter.project_name}}/{{cookiecutter.package_name}}/core/exceptions.py
pytemplate_uv-0.1.0.dist-info/LICENSE
pytemplate_uv-0.1.0.dist-info/METADATA
pytemplate_uv-0.1.0.dist-info/WHEEL
pytemplate_uv-0.1.0.dist-info/entry_points.txt
pytemplate_uv-0.1.0.dist-info/top_level.txt
pytemplate_uv-0.1.0.dist-info/RECORD
