Metadata-Version: 2.2
Name: pytemplate-uv
Version: 0.1.0
Summary: A template for creating Python projects using uv package manager
Author-email: Leo Liu <yuxuzi@gmail.com>
License: MIT
Project-URL: Homepage, https://github.com/yuxuzi/pytemplate-uv
Project-URL: Repository, https://github.com/yuxuzi/pytemplate-uv
Project-URL: Issues, https://github.com/yuxuzi/pytemplate-uv/issues
Project-URL: Changelog, https://github.com/yuxuzi/pytemplate-uv/blob/main/CHANGELOG.md
Keywords: python,template,project-generator,uv,cookiecutter,cli
Classifier: Development Status :: 3 - Alpha
Classifier: Intended Audience :: Developers
Classifier: License :: OSI Approved :: MIT License
Classifier: Programming Language :: Python :: 3.11
Classifier: Programming Language :: Python :: 3.12
Classifier: Topic :: Software Development :: Libraries :: Python Modules
Classifier: Topic :: Utilities
Classifier: Typing :: Typed
Requires-Python: >=3.11
License-File: LICENSE
Requires-Dist: typer>=0.9.0
Requires-Dist: rich>=13.7.0
Requires-Dist: cookiecutter>=2.5.0
Requires-Dist: pytest>=7.4.4
Provides-Extra: dev
Requires-Dist: ruff>=0.1.9; extra == "dev"
Requires-Dist: black>=23.12.1; extra == "dev"
Requires-Dist: pytest>=7.4.4; extra == "dev"
Requires-Dist: pre-commit>=3.6.0; extra == "dev"
Requires-Dist: mypy>=1.7.1; extra == "dev"
Requires-Dist: coverage>=7.3.2; extra == "dev"
Provides-Extra: docs
Requires-Dist: mkdocs>=1.5.3; extra == "docs"
Requires-Dist: mkdocstrings[python]>=0.24.0; extra == "docs"
